rfinder/__init__.py
rfinder/main.py
rfinder/rfi.py
rfinder/rfinder_default.yml
rfinder/rfinder_files.py
rfinder/rfinder_plots.py
rfinder/rfinder_stats.py
rfinder/templates/full_template.html
rfinder/templates/fullshort_template.html
rfinder/templates/summary_template.html
rfinder/templates/time_template.html
rfinder-1.1.0.dist-info/LICENSE.md
rfinder-1.1.0.dist-info/METADATA
rfinder-1.1.0.dist-info/WHEEL
rfinder-1.1.0.dist-info/entry_points.txt
rfinder-1.1.0.dist-info/RECORD
