Metadata-Version: 2.1
Name: rfinder
Version: 1.1.0
Summary: Tool for identify the presence of RFI in an observation, flagging and visualisation
Home-page: https://github.com/caracal-pipeline/rfinder
License: GNU GPL v3
Keywords: Astronomy,Visualisation,RFI
Author: Filippo Marcello Maccagni
Author-email: filippo.maccagni@gmail.com
Requires-Python: >=3.8,<4.0
Classifier: Development Status :: 5 - Production/Stable
Classifier: Intended Audience :: Science/Research
Classifier: License :: OSI Approved :: GNU General Public License v3 (GPLv3)
Classifier: License :: Other/Proprietary License
Classifier: Operating System :: POSIX :: Linux
Classifier: Programming Language :: Python :: 3
Classifier: Programming Language :: Python :: 3.8
Classifier: Programming Language :: Python :: 3.9
Classifier: Programming Language :: Python :: 3.10
Classifier: Programming Language :: Python :: 3.11
Classifier: Programming Language :: Python :: 3
Classifier: Topic :: Scientific/Engineering :: Astronomy
Classifier: Topic :: Software Development :: Libraries :: Python Modules
Provides-Extra: testing
Requires-Dist: astropy (>=5.2.1,<6.0.0)
Requires-Dist: ffmpeg (>=1.4,<2.0)
Requires-Dist: imageio (>=2.27.0,<3.0.0)
Requires-Dist: ipython (>=8.12.0,<9.0.0)
Requires-Dist: jinja2 (>=3.1.2,<4.0.0)
Requires-Dist: matplotlib (>=3.7.1,<4.0.0)
Requires-Dist: numpy (>=1.24.2,<2.0.0)
Requires-Dist: pyaml (>=21.10.1,<22.0.0)
Requires-Dist: pytest (>=7.2.2,<8.0.0) ; extra == "testing"
Requires-Dist: pytest-flake8 (>=1.1.1,<2.0.0) ; extra == "testing"
Requires-Dist: python-casacore (>=3.5.2,<4.0.0)
Requires-Dist: scipy (>=1.9.3,<2.0.0)
Project-URL: Repository, https://github.com/caracal-pipeline/rfinder
